e2b_on_fc/README.md
e2b_on_fc/__init__.py
e2b_on_fc/pyproject.toml
e2b_on_fc/simple_sandbox.py
e2b_on_fc/e2b/__init__.py
e2b_on_fc/e2b/connection_config.py
e2b_on_fc/e2b/exceptions.py
e2b_on_fc/e2b/api/__init__.py
e2b_on_fc/e2b/api/metadata.py
e2b_on_fc/e2b/api/client/__init__.py
e2b_on_fc/e2b/api/client/client.py
e2b_on_fc/e2b/api/client/errors.py
e2b_on_fc/e2b/api/client/py.typed
e2b_on_fc/e2b/api/client/types.py
e2b_on_fc/e2b/api/client/api/__init__.py
e2b_on_fc/e2b/api/client/api/sandboxes/__init__.py
e2b_on_fc/e2b/api/client/api/sandboxes/delete_sandboxes_sandbox_id.py
e2b_on_fc/e2b/api/client/api/sandboxes/get_sandboxes.py
e2b_on_fc/e2b/api/client/api/sandboxes/get_sandboxes_metrics.py
e2b_on_fc/e2b/api/client/api/sandboxes/get_sandboxes_sandbox_id.py
e2b_on_fc/e2b/api/client/api/sandboxes/get_sandboxes_sandbox_id_logs.py
e2b_on_fc/e2b/api/client/api/sandboxes/get_sandboxes_sandbox_id_metrics.py
e2b_on_fc/e2b/api/client/api/sandboxes/get_v2_sandboxes.py
e2b_on_fc/e2b/api/client/api/sandboxes/post_sandboxes.py
e2b_on_fc/e2b/api/client/api/sandboxes/post_sandboxes_sandbox_id_pause.py
e2b_on_fc/e2b/api/client/api/sandboxes/post_sandboxes_sandbox_id_refreshes.py
e2b_on_fc/e2b/api/client/api/sandboxes/post_sandboxes_sandbox_id_resume.py
e2b_on_fc/e2b/api/client/api/sandboxes/post_sandboxes_sandbox_id_timeout.py
e2b_on_fc/e2b/api/client/models/__init__.py
e2b_on_fc/e2b/api/client/models/created_access_token.py
e2b_on_fc/e2b/api/client/models/created_team_api_key.py
e2b_on_fc/e2b/api/client/models/error.py
e2b_on_fc/e2b/api/client/models/listed_sandbox.py
e2b_on_fc/e2b/api/client/models/new_access_token.py
e2b_on_fc/e2b/api/client/models/new_sandbox.py
e2b_on_fc/e2b/api/client/models/new_team_api_key.py
e2b_on_fc/e2b/api/client/models/node.py
e2b_on_fc/e2b/api/client/models/node_detail.py
e2b_on_fc/e2b/api/client/models/node_status.py
e2b_on_fc/e2b/api/client/models/node_status_change.py
e2b_on_fc/e2b/api/client/models/post_sandboxes_sandbox_id_refreshes_body.py
fc_code_interpreter_mcp_server-0.0.10.dist-info/METADATA
fc_code_interpreter_mcp_server-0.0.10.dist-info/WHEEL
fc_code_interpreter_mcp_server-0.0.10.dist-info/entry_points.txt
fc_code_interpreter_mcp_server-0.0.10.dist-info/licenses/LICENSE
fc_code_interpreter_mcp_server-0.0.10.dist-info/RECORD
