Metadata-Version: 2.4
Name: fc-code-interpreter-mcp-server
Version: 0.0.10
Summary: Code Interpreter MCP Server - Secure code execution via E2B on Function Compute
Project-URL: Homepage, https://github.com/alibaba/fc-code-interpreter-mcp-server
Project-URL: Repository, https://github.com/alibaba/fc-code-interpreter-mcp-server
Project-URL: Documentation, https://github.com/alibaba/fc-code-interpreter-mcp-server#readme
Project-URL: Issues, https://github.com/alibaba/fc-code-interpreter-mcp-server/issues
Author-email: Function Compute Team <fc-team@alibaba-inc.com>
License: MIT
License-File: LICENSE
Keywords: code-interpreter,e2b,function-compute,mcp,sandbox
Classifier: Development Status :: 4 - Beta
Classifier: Intended Audience :: Developers
Classifier: License :: OSI Approved :: MIT License
Classifier: Programming Language :: Python :: 3
Classifier: Programming Language :: Python :: 3.10
Classifier: Programming Language :: Python :: 3.11
Classifier: Programming Language :: Python :: 3.12
Classifier: Topic :: Software Development :: Libraries :: Python Modules
Classifier: Topic :: System :: Distributed Computing
Requires-Python: >=3.10
Requires-Dist: alibabacloud-credentials-api>=1.0.0
Requires-Dist: alibabacloud-credentials>=1.0.2
Requires-Dist: alibabacloud-endpoint-util>=0.0.4
Requires-Dist: alibabacloud-fc20230330>=4.2.7
Requires-Dist: alibabacloud-gateway-spi>=0.0.3
Requires-Dist: alibabacloud-openapi-util>=0.2.2
Requires-Dist: alibabacloud-tea-openapi>=0.3.16
Requires-Dist: alibabacloud-tea-util>=0.3.13
Requires-Dist: alibabacloud-tea>=0.4.3
Requires-Dist: attrs>=25.3.0
Requires-Dist: certifi>=2025.7.14
Requires-Dist: charset-normalizer>=3.4.2
Requires-Dist: e2b-code-interpreter>=0.8.0
Requires-Dist: e2b>=0.8.0
Requires-Dist: fastmcp>=2.12.5
Requires-Dist: httpcore>=1.0.9
Requires-Dist: httpx>=0.28.1
Requires-Dist: idna>=3.10
Requires-Dist: mcp>=1.0.0
Requires-Dist: packaging>=23.0
Requires-Dist: protobuf>=5.29.5
Requires-Dist: pydantic>=2.10.2
Requires-Dist: python-dateutil>=2.8.0
Requires-Dist: python-dotenv>=1.0.1
Requires-Dist: requests>=2.31.0
Requires-Dist: six>=1.16.0
Requires-Dist: starlette>=0.36.0
Requires-Dist: typing-extensions>=4.14.1
Requires-Dist: urllib3>=2.5.0
Requires-Dist: uvicorn>=0.27.0
